Vivado/src/DRXsimulator/ip_repo/counterConfig_1_0/hdl/counterConfig_v1_0_S00_AXI.vhd
library ieee;
use ieee.std_logic_1164.all;
use ieee.numeric_std.all;

entity counterConfig_v1_0_S00_AXI is
  generic
  (
    -- Users to add parameters here
    counter_bits : integer := 16;
    -- User parameters ends
    -- Do not modify the parameters beyond this line

    -- Width of S_AXI data bus
    C_S_AXI_DATA_WIDTH : integer := 32;
    -- Width of S_AXI address bus
    C_S_AXI_ADDR_WIDTH : integer := 4
  );
  port
  (
    -- Users to add ports here
    freq_div  : out std_logic; -- 125m or 250m cells
    max_count : out std_logic_vector (counter_bits - 1 downto 0); -- Count to restart the counter
    enable    : out std_logic; -- enable the counter
    -- User ports ends
    -- Do not modify the ports beyond this line

    -- Global Clock Signal
    S_AXI_ACLK : in std_logic;
    -- Global Reset Signal. This Signal is Active LOW
    S_AXI_ARESETN : in std_logic;
    -- Write address (issued by master, acceped by Slave)
    S_AXI_AWADDR : in std_logic_vector(C_S_AXI_ADDR_WIDTH - 1 downto 0);
    -- Write channel Protection type. This signal indicates the
    -- privilege and security level of the transaction, and whether
    -- the transaction is a data access or an instruction access.
    S_AXI_AWPROT : in std_logic_vector(2 downto 0);
    -- Write address valid. This signal indicates that the master signaling
    -- valid write address and control information.
    S_AXI_AWVALID : in std_logic;
    -- Write address ready. This signal indicates that the slave is ready
    -- to accept an address and associated control signals.
    S_AXI_AWREADY : out std_logic;
    -- Write data (issued by master, acceped by Slave) 
    S_AXI_WDATA : in std_logic_vector(C_S_AXI_DATA_WIDTH - 1 downto 0);
    -- Write strobes. This signal indicates which byte lanes hold
    -- valid data. There is one write strobe bit for each eight
    -- bits of the write data bus.    
    S_AXI_WSTRB : in std_logic_vector((C_S_AXI_DATA_WIDTH/8) - 1 downto 0);
    -- Write valid. This signal indicates that valid write
    -- data and strobes are available.
    S_AXI_WVALID : in std_logic;
    -- Write ready. This signal indicates that the slave
    -- can accept the write data.
    S_AXI_WREADY : out std_logic;
    -- Write response. This signal indicates the status
    -- of the write transaction.
    S_AXI_BRESP : out std_logic_vector(1 downto 0);
    -- Write response valid. This signal indicates that the channel
    -- is signaling a valid write response.
    S_AXI_BVALID : out std_logic;
    -- Response ready. This signal indicates that the master
    -- can accept a write response.
    S_AXI_BREADY : in std_logic;
    -- Read address (issued by master, acceped by Slave)
    S_AXI_ARADDR : in std_logic_vector(C_S_AXI_ADDR_WIDTH - 1 downto 0);
    -- Protection type. This signal indicates the privilege
    -- and security level of the transaction, and whether the
    -- transaction is a data access or an instruction access.
    S_AXI_ARPROT : in std_logic_vector(2 downto 0);
    -- Read address valid. This signal indicates that the channel
    -- is signaling valid read address and control information.
    S_AXI_ARVALID : in std_logic;
    -- Read address ready. This signal indicates that the slave is
    -- ready to accept an address and associated control signals.
    S_AXI_ARREADY : out std_logic;
    -- Read data (issued by slave)
    S_AXI_RDATA : out std_logic_vector(C_S_AXI_DATA_WIDTH - 1 downto 0);
    -- Read response. This signal indicates the status of the
    -- read transfer.
    S_AXI_RRESP : out std_logic_vector(1 downto 0);
    -- Read valid. This signal indicates that the channel is
    -- signaling the required read data.
    S_AXI_RVALID : out std_logic;
    -- Read ready. This signal indicates that the master can
    -- accept the read data and response information.
    S_AXI_RREADY : in std_logic
  );
end counterConfig_v1_0_S00_AXI;

architecture arch_imp of counterConfig_v1_0_S00_AXI is

  -- AXI4LITE signals
  signal axi_awaddr  : std_logic_vector(C_S_AXI_ADDR_WIDTH - 1 downto 0);
  signal axi_awready : std_logic;
  signal axi_wready  : std_logic;
  signal axi_bresp   : std_logic_vector(1 downto 0);
  signal axi_bvalid  : std_logic;
  signal axi_araddr  : std_logic_vector(C_S_AXI_ADDR_WIDTH - 1 downto 0);
  signal axi_arready : std_logic;
  signal axi_rdata   : std_logic_vector(C_S_AXI_DATA_WIDTH - 1 downto 0);
  signal axi_rresp   : std_logic_vector(1 downto 0);
  signal axi_rvalid  : std_logic;

  -- Example-specific design signals
  -- local parameter for addressing 32 bit / 64 bit C_S_AXI_DATA_WIDTH
  -- ADDR_LSB is used for addressing 32/64 bit registers/memories
  -- ADDR_LSB = 2 for 32 bits (n downto 2)
  -- ADDR_LSB = 3 for 64 bits (n downto 3)
  constant ADDR_LSB          : integer := (C_S_AXI_DATA_WIDTH/32) + 1;
  constant OPT_MEM_ADDR_BITS : integer := 1;
  ------------------------------------------------
  ---- Signals for user logic register space example
  --------------------------------------------------
  ---- Number of Slave Registers 4
  signal slv_reg0     : std_logic_vector(C_S_AXI_DATA_WIDTH - 1 downto 0);
  signal slv_reg1     : std_logic_vector(C_S_AXI_DATA_WIDTH - 1 downto 0);
  signal slv_reg2     : std_logic_vector(C_S_AXI_DATA_WIDTH - 1 downto 0);
  signal slv_reg3     : std_logic_vector(C_S_AXI_DATA_WIDTH - 1 downto 0);
  signal slv_reg_rden : std_logic;
  signal slv_reg_wren : std_logic;
  signal reg_data_out : std_logic_vector(C_S_AXI_DATA_WIDTH - 1 downto 0);
  --signal byte_index	: integer;
  signal aw_en : std_logic;

begin
  -- I/O Connections assignments

  S_AXI_AWREADY <= axi_awready;
  S_AXI_WREADY  <= axi_wready;
  S_AXI_BRESP   <= axi_bresp;
  S_AXI_BVALID  <= axi_bvalid;
  S_AXI_ARREADY <= axi_arready;
  S_AXI_RDATA   <= axi_rdata;
  S_AXI_RRESP   <= axi_rresp;
  S_AXI_RVALID  <= axi_rvalid;
  -- Implement axi_awready generation
  -- axi_awready is asserted for one S_AXI_ACLK clock cycle when both
  -- S_AXI_AWVALID and S_AXI_WVALID are asserted. axi_awready is
  -- de-asserted when reset is low.

  process (S_AXI_ACLK)
  begin
    if rising_edge(S_AXI_ACLK) then
      if S_AXI_ARESETN = '0' then
        axi_awready <= '0';
        aw_en       <= '1';
      else
        if (axi_awready = '0' and S_AXI_AWVALID = '1' and S_AXI_WVALID = '1' and aw_en = '1') then
          -- slave is ready to accept write address when
          -- there is a valid write address and write data
          -- on the write address and data bus. This design 
          -- expects no outstanding transactions. 
          axi_awready <= '1';
          aw_en       <= '0';
        elsif (S_AXI_BREADY = '1' and axi_bvalid = '1') then
          aw_en       <= '1';
          axi_awready <= '0';
        else
          axi_awready <= '0';
        end if;
      end if;
    end if;
  end process;

  -- Implement axi_awaddr latching
  -- This process is used to latch the address when both 
  -- S_AXI_AWVALID and S_AXI_WVALID are valid. 

  process (S_AXI_ACLK)
  begin
    if rising_edge(S_AXI_ACLK) then
      if S_AXI_ARESETN = '0' then
        axi_awaddr <= (others => '0');
      else
        if (axi_awready = '0' and S_AXI_AWVALID = '1' and S_AXI_WVALID = '1' and aw_en = '1') then
          -- Write Address latching
          axi_awaddr <= S_AXI_AWADDR;
        end if;
      end if;
    end if;
  end process;

  -- Implement axi_wready generation
  -- axi_wready is asserted for one S_AXI_ACLK clock cycle when both
  -- S_AXI_AWVALID and S_AXI_WVALID are asserted. axi_wready is 
  -- de-asserted when reset is low. 

  process (S_AXI_ACLK)
  begin
    if rising_edge(S_AXI_ACLK) then
      if S_AXI_ARESETN = '0' then
        axi_wready <= '0';
      else
        if (axi_wready = '0' and S_AXI_WVALID = '1' and S_AXI_AWVALID = '1' and aw_en = '1') then
          -- slave is ready to accept write data when 
          -- there is a valid write address and write data
          -- on the write address and data bus. This design 
          -- expects no outstanding transactions.           
          axi_wready <= '1';
        else
          axi_wready <= '0';
        end if;
      end if;
    end if;
  end process;

  -- Implement memory mapped register select and write logic generation
  -- The write data is accepted and written to memory mapped registers when
  -- axi_awready, S_AXI_WVALID, axi_wready and S_AXI_WVALID are asserted. Write strobes are used to
  -- select byte enables of slave registers while writing.
  -- These registers are cleared when reset (active low) is applied.
  -- Slave register write enable is asserted when valid address and data are available
  -- and the slave is ready to accept the write address and write data.
  slv_reg_wren <= axi_wready and S_AXI_WVALID and axi_awready and S_AXI_AWVALID;

  process (S_AXI_ACLK)
    variable loc_addr : std_logic_vector(OPT_MEM_ADDR_BITS downto 0);
  begin
    if rising_edge(S_AXI_ACLK) then
      if S_AXI_ARESETN = '0' then
        slv_reg0 <= (others => '0');
        slv_reg1 <= (others => '0');
        slv_reg2 <= (others => '0');
        slv_reg3 <= (others => '0');
      else
        loc_addr := axi_awaddr(ADDR_LSB + OPT_MEM_ADDR_BITS downto ADDR_LSB);
        if (slv_reg_wren = '1') then
          case loc_addr is
            when b"00" =>
              for byte_index in 0 to (C_S_AXI_DATA_WIDTH/8 - 1) loop
                if (S_AXI_WSTRB(byte_index) = '1') then
                  -- Respective byte enables are asserted as per write strobes                   
                  -- slave registor 0
                  slv_reg0(byte_index * 8 + 7 downto byte_index * 8) <= S_AXI_WDATA(byte_index * 8 + 7 downto byte_index * 8);
                end if;
              end loop;
            when b"01" =>
              for byte_index in 0 to (C_S_AXI_DATA_WIDTH/8 - 1) loop
                if (S_AXI_WSTRB(byte_index) = '1') then
                  -- Respective byte enables are asserted as per write strobes                   
                  -- slave registor 1
                  slv_reg1(byte_index * 8 + 7 downto byte_index * 8) <= S_AXI_WDATA(byte_index * 8 + 7 downto byte_index * 8);
                end if;
              end loop;
            when b"10" =>
              for byte_index in 0 to (C_S_AXI_DATA_WIDTH/8 - 1) loop
                if (S_AXI_WSTRB(byte_index) = '1') then
                  -- Respective byte enables are asserted as per write strobes                   
                  -- slave registor 2
                  slv_reg2(byte_index * 8 + 7 downto byte_index * 8) <= S_AXI_WDATA(byte_index * 8 + 7 downto byte_index * 8);
                end if;
              end loop;
            when b"11" =>
              for byte_index in 0 to (C_S_AXI_DATA_WIDTH/8 - 1) loop
                if (S_AXI_WSTRB(byte_index) = '1') then
                  -- Respective byte enables are asserted as per write strobes                   
                  -- slave registor 3
                  slv_reg3(byte_index * 8 + 7 downto byte_index * 8) <= S_AXI_WDATA(byte_index * 8 + 7 downto byte_index * 8);
                end if;
              end loop;
            when others =>
              slv_reg0 <= slv_reg0;
              slv_reg1 <= slv_reg1;
              slv_reg2 <= slv_reg2;
              slv_reg3 <= slv_reg3;
          end case;
        end if;
      end if;
    end if;
  end process;

  -- Implement write response logic generation
  -- The write response and response valid signals are asserted by the slave 
  -- when axi_wready, S_AXI_WVALID, axi_wready and S_AXI_WVALID are asserted.  
  -- This marks the acceptance of address and indicates the status of 
  -- write transaction.

  process (S_AXI_ACLK)
  begin
    if rising_edge(S_AXI_ACLK) then
      if S_AXI_ARESETN = '0' then
        axi_bvalid <= '0';
        axi_bresp  <= "00"; --need to work more on the responses
      else
        if (axi_awready = '1' and S_AXI_AWVALID = '1' and axi_wready = '1' and S_AXI_WVALID = '1' and axi_bvalid = '0') then
          axi_bvalid <= '1';
          axi_bresp  <= "00";
        elsif (S_AXI_BREADY = '1' and axi_bvalid = '1') then --check if bready is asserted while bvalid is high)
          axi_bvalid <= '0'; -- (there is a possibility that bready is always asserted high)
        end if;
      end if;
    end if;
  end process;

  -- Implement axi_arready generation
  -- axi_arready is asserted for one S_AXI_ACLK clock cycle when
  -- S_AXI_ARVALID is asserted. axi_awready is 
  -- de-asserted when reset (active low) is asserted. 
  -- The read address is also latched when S_AXI_ARVALID is 
  -- asserted. axi_araddr is reset to zero on reset assertion.

  process (S_AXI_ACLK)
  begin
    if rising_edge(S_AXI_ACLK) then
      if S_AXI_ARESETN = '0' then
        axi_arready <= '0';
        axi_araddr  <= (others => '1');
      else
        if (axi_arready = '0' and S_AXI_ARVALID = '1') then
          -- indicates that the slave has acceped the valid read address
          axi_arready <= '1';
          -- Read Address latching 
          axi_araddr <= S_AXI_ARADDR;
        else
          axi_arready <= '0';
        end if;
      end if;
    end if;
  end process;

  -- Implement axi_arvalid generation
  -- axi_rvalid is asserted for one S_AXI_ACLK clock cycle when both 
  -- S_AXI_ARVALID and axi_arready are asserted. The slave registers 
  -- data are available on the axi_rdata bus at this instance. The 
  -- assertion of axi_rvalid marks the validity of read data on the 
  -- bus and axi_rresp indicates the status of read transaction.axi_rvalid 
  -- is deasserted on reset (active low). axi_rresp and axi_rdata are 
  -- cleared to zero on reset (active low).  
  process (S_AXI_ACLK)
  begin
    if rising_edge(S_AXI_ACLK) then
      if S_AXI_ARESETN = '0' then
        axi_rvalid <= '0';
        axi_rresp  <= "00";
      else
        if (axi_arready = '1' and S_AXI_ARVALID = '1' and axi_rvalid = '0') then
          -- Valid read data is available at the read data bus
          axi_rvalid <= '1';
          axi_rresp  <= "00"; -- 'OKAY' response
        elsif (axi_rvalid = '1' and S_AXI_RREADY = '1') then
          -- Read data is accepted by the master
          axi_rvalid <= '0';
        end if;
      end if;
    end if;
  end process;

  -- Implement memory mapped register select and read logic generation
  -- Slave register read enable is asserted when valid address is available
  -- and the slave is ready to accept the read address.
  slv_reg_rden <= axi_arready and S_AXI_ARVALID and (not axi_rvalid);

  process (slv_reg0, slv_reg1, slv_reg2, slv_reg3, axi_araddr, S_AXI_ARESETN, slv_reg_rden)
    variable loc_addr : std_logic_vector(OPT_MEM_ADDR_BITS downto 0);
  begin
    -- Address decoding for reading registers
    loc_addr := axi_araddr(ADDR_LSB + OPT_MEM_ADDR_BITS downto ADDR_LSB);
    case loc_addr is
      when b"00" =>
        reg_data_out <= slv_reg0;
      when b"01" =>
        reg_data_out <= slv_reg1;
      when b"10" =>
        reg_data_out <= slv_reg2;
      when b"11" =>
        reg_data_out <= slv_reg3;
      when others             =>
        reg_data_out <= (others => '0');
    end case;
  end process;

  -- Output register or memory read data
  process (S_AXI_ACLK) is
  begin
    if (rising_edge (S_AXI_ACLK)) then
      if (S_AXI_ARESETN = '0') then
        axi_rdata <= (others => '0');
      else
        if (slv_reg_rden = '1') then
          -- When there is a valid read address (S_AXI_ARVALID) with 
          -- acceptance of read address by the slave (axi_arready), 
          -- output the read dada 
          -- Read address mux
          axi_rdata <= reg_data_out; -- register read data
        end if;
      end if;
    end if;
  end process;
  -- Add user logic here
  freq_div  <= slv_reg0(0);
  enable    <= slv_reg1(0);
  max_count <= slv_reg2(counter_bits - 1 downto 0);
  -- User logic ends

end arch_imp;

Vivado/src/DRXsimulator/ip_repo/counterConfig_1_0/src/counterConfig_v1_0_S00_AXI_tb.vhd
library ieee;
use ieee.std_logic_1164.all;
use ieee.numeric_std.all;

entity counterConfig_v1_0_S00_AXI_tb is
end counterConfig_v1_0_S00_AXI_tb;

architecture tb_arch of counterConfig_v1_0_S00_AXI_tb is
  -- Component Declaration
  component counterConfig_v1_0_S00_AXI is
    generic
    (
      counter_bits       : integer := 16;
      C_S_AXI_DATA_WIDTH : integer := 32;
      C_S_AXI_ADDR_WIDTH : integer := 4
    );
    port
    (
      freq_div      : out std_logic;
      max_count     : out std_logic_vector (counter_bits - 1 downto 0);
      enable        : out std_logic;
      S_AXI_ACLK    : in std_logic;
      S_AXI_ARESETN : in std_logic;
      S_AXI_AWADDR  : in std_logic_vector(C_S_AXI_ADDR_WIDTH - 1 downto 0);
      S_AXI_AWPROT  : in std_logic_vector(2 downto 0);
      S_AXI_AWVALID : in std_logic;
      S_AXI_AWREADY : out std_logic;
      S_AXI_WDATA   : in std_logic_vector(C_S_AXI_DATA_WIDTH - 1 downto 0);
      S_AXI_WSTRB   : in std_logic_vector((C_S_AXI_DATA_WIDTH/8) - 1 downto 0);
      S_AXI_WVALID  : in std_logic;
      S_AXI_WREADY  : out std_logic;
      S_AXI_BRESP   : out std_logic_vector(1 downto 0);
      S_AXI_BVALID  : out std_logic;
      S_AXI_BREADY  : in std_logic;
      S_AXI_ARADDR  : in std_logic_vector(C_S_AXI_ADDR_WIDTH - 1 downto 0);
      S_AXI_ARPROT  : in std_logic_vector(2 downto 0);
      S_AXI_ARVALID : in std_logic;
      S_AXI_ARREADY : out std_logic;
      S_AXI_RDATA   : out std_logic_vector(C_S_AXI_DATA_WIDTH - 1 downto 0);
      S_AXI_RRESP   : out std_logic_vector(1 downto 0);
      S_AXI_RVALID  : out std_logic;
      S_AXI_RREADY  : in std_logic
    );
  end component;

  -- Component signals
  signal S_AXI_ACLK    : std_logic                    := '0';
  signal S_AXI_ARESETN : std_logic                    := '0';
  signal S_AXI_AWADDR  : std_logic_vector(3 downto 0) := (others => '0');
  signal S_AXI_AWPROT  : std_logic_vector(2 downto 0) := (others => '0');
  signal S_AXI_AWVALID : std_logic                    := '0';
  signal S_AXI_AWREADY : std_logic;
  signal S_AXI_WDATA   : std_logic_vector(31 downto 0) := (others => '0');
  signal S_AXI_WSTRB   : std_logic_vector(3 downto 0)  := (others => '0');
  signal S_AXI_WVALID  : std_logic                     := '0';
  signal S_AXI_WREADY  : std_logic;
  signal S_AXI_BRESP   : std_logic_vector(1 downto 0);
  signal S_AXI_BVALID  : std_logic;
  signal S_AXI_BREADY  : std_logic;
  signal S_AXI_ARADDR  : std_logic_vector(3 downto 0) := (others => '0');
  signal S_AXI_ARPROT  : std_logic_vector(2 downto 0) := (others => '0');
  signal S_AXI_ARVALID : std_logic                    := '0';
  signal S_AXI_ARREADY : std_logic;
  signal S_AXI_RDATA   : std_logic_vector(31 downto 0);
  signal S_AXI_RRESP   : std_logic_vector(1 downto 0);
  signal S_AXI_RVALID  : std_logic;
  signal S_AXI_RREADY  : std_logic;

  constant ClockPeriod  : time      := 5 ns;
  constant ClockPeriod2 : time      := 10 ns;
  signal sendIt         : std_logic := '0';
  signal readIt         : std_logic := '0';
  -- Signals
  signal freq_div  : std_logic;
  signal max_count : std_logic_vector (15 downto 0);
  signal enable    : std_logic;
begin

  -- Instantiate the component
  uut : counterConfig_v1_0_S00_AXI
  generic
  map (
  counter_bits       => 16,
  C_S_AXI_DATA_WIDTH => 32,
  C_S_AXI_ADDR_WIDTH => 4
  )
  port map
  (
    freq_div      => freq_div,
    max_count     => max_count,
    enable        => enable,
    S_AXI_ACLK    => S_AXI_ACLK,
    S_AXI_ARESETN => S_AXI_ARESETN,
    S_AXI_AWADDR  => S_AXI_AWADDR,
    S_AXI_AWPROT  => S_AXI_AWPROT,
    S_AXI_AWVALID => S_AXI_AWVALID,
    S_AXI_AWREADY => S_AXI_AWREADY,
    S_AXI_WDATA   => S_AXI_WDATA,
    S_AXI_WSTRB   => S_AXI_WSTRB,
    S_AXI_WVALID  => S_AXI_WVALID,
    S_AXI_WREADY  => S_AXI_WREADY,
    S_AXI_BRESP   => S_AXI_BRESP,
    S_AXI_BVALID  => S_AXI_BVALID,
    S_AXI_BREADY  => S_AXI_BREADY,
    S_AXI_ARADDR  => S_AXI_ARADDR,
    S_AXI_ARPROT  => S_AXI_ARPROT,
    S_AXI_ARVALID => S_AXI_ARVALID,
    S_AXI_ARREADY => S_AXI_ARREADY,
    S_AXI_RDATA   => S_AXI_RDATA,
    S_AXI_RRESP   => S_AXI_RRESP,
    S_AXI_RVALID  => S_AXI_RVALID,
    S_AXI_RREADY  => S_AXI_RREADY
  );

  -- Generate S_AXI_ACLK signal
  GENERATE_REFCLOCK : process
  begin
    wait for (ClockPeriod / 2);
    S_AXI_ACLK <= '1';
    wait for (ClockPeriod / 2);
    S_AXI_ACLK <= '0';
  end process;

  -- Initiate process which simulates a master wanting to write.
  -- This process is blocked on a "Send Flag" (sendIt).
  -- When the flag goes to 1, the process exits the wait state and
  -- execute a write transaction.
  send : process
  begin
    S_AXI_AWVALID <= '0';
    S_AXI_WVALID  <= '0';
    S_AXI_BREADY  <= '0';
    loop
      wait until sendIt = '1';
      wait until S_AXI_ACLK = '0';
      S_AXI_AWVALID <= '1';
      S_AXI_WVALID  <= '1';
      wait until (S_AXI_AWREADY and S_AXI_WREADY) = '1'; --Client ready to read address/data        
      S_AXI_BREADY <= '1';
      wait until S_AXI_BVALID = '1'; -- Write result valid
      assert S_AXI_BRESP = "00" report "AXI data not written" severity failure;
      S_AXI_AWVALID <= '0';
      S_AXI_WVALID  <= '0';
      S_AXI_BREADY  <= '1';
      wait until S_AXI_BVALID = '0'; -- All finished
      S_AXI_BREADY <= '0';
    end loop;
  end process send;

  -- Initiate process which simulates a master wanting to read.
  -- This process is blocked on a "Read Flag" (readIt).
  -- When the flag goes to 1, the process exits the wait state and
  -- execute a read transaction.
  read : process
  begin
    S_AXI_ARVALID <= '0';
    S_AXI_RREADY  <= '0';
    loop
      wait until readIt = '1';
      wait until S_AXI_ACLK = '0';
      S_AXI_ARVALID <= '1';
      S_AXI_RREADY  <= '1';
      wait until (S_AXI_RVALID and S_AXI_ARREADY) = '1'; --Client provided data
      assert S_AXI_RRESP = "00" report "AXI data not written" severity failure;
      S_AXI_ARVALID <= '0';
      S_AXI_RREADY  <= '0';
    end loop;
  end process read;
  -- 
  tb : process
  begin
    S_AXI_ARESETN <= '0';
    sendIt        <= '0';
    wait for 15 ns;
    S_AXI_ARESETN <= '1';

    S_AXI_AWADDR <= x"0";
    S_AXI_WDATA  <= x"00000001"; -- Freq div = 1
    S_AXI_WSTRB  <= b"1111";
    sendIt       <= '1'; --Start AXI Write to Slave
    wait for 1 ns;
    sendIt <= '0'; --Clear Start Send Flag
    wait until S_AXI_BVALID = '1';
    wait until S_AXI_BVALID = '0'; --AXI Write finished
    S_AXI_WSTRB <= b"0000";

    S_AXI_AWADDR <= x"4";
    S_AXI_WDATA  <= x"00000001"; -- Enable = 1
    S_AXI_WSTRB  <= b"1111";
    sendIt       <= '1'; --Start AXI Write to Slave
    wait for 1 ns;
    sendIt <= '0'; --Clear Start Send Flag
    wait until S_AXI_BVALID = '1';
    wait until S_AXI_BVALID = '0'; --AXI Write finished
    S_AXI_WSTRB <= b"0000";

    S_AXI_AWADDR <= x"8";
    S_AXI_WDATA  <= x"00000300"; -- Max count = 1024
    S_AXI_WSTRB  <= b"1111";
    sendIt       <= '1'; --Start AXI Write to Slave
    wait for 1 ns;
    sendIt <= '0'; --Clear Start Send Flag
    wait until S_AXI_BVALID = '1';
    wait until S_AXI_BVALID = '0'; --AXI Write finished
    S_AXI_WSTRB <= b"0000";

    S_AXI_AWADDR <= x"0";
    S_AXI_WDATA  <= x"00000000";
    S_AXI_WSTRB  <= b"1111";
    sendIt       <= '1'; --Start AXI Write to Slave
    wait for 1 ns;
    sendIt <= '0'; --Clear Start Send Flag
    wait until S_AXI_BVALID = '1';
    wait until S_AXI_BVALID = '0'; --AXI Write finished
    S_AXI_WSTRB <= b"0000";

    S_AXI_ARADDR <= x"0";
    readIt       <= '1'; --Start AXI Read from Slave
    wait for 1 ns;
    readIt <= '0'; --Clear "Start Read" Flag
    wait until S_AXI_RVALID = '1';
    wait until S_AXI_RVALID = '0';
    S_AXI_ARADDR <= x"4";
    readIt       <= '1'; --Start AXI Read from Slave
    wait for 1 ns;
    readIt <= '0'; --Clear "Start Read" Flag
    wait until S_AXI_RVALID = '1';
    wait until S_AXI_RVALID = '0';

    -- Add more test cases as needed
    wait; -- will wait forever
  end process tb;

end tb_arch;

Vivado/src/DRXsimulator/ip_repo/counterConfig_1_0/hdl/sim.vcd
$date
  Fri Oct 27 21:27:49 2023
$end
$version
  GHDL v0
$end
$timescale
  1 fs
$end
$scope module standard $end
$upscope $end
$scope module std_logic_1164 $end
$upscope $end
$scope module numeric_std $end
$upscope $end
$scope module counterconfig_v1_0_s00_axi_tb $end
$var reg 1 ! s_axi_aclk $end
$var reg 1 " s_axi_aresetn $end
$var reg 4 # s_axi_awaddr[3:0] $end
$var reg 3 $ s_axi_awprot[2:0] $end
$var reg 1 % s_axi_awvalid $end
$var reg 1 & s_axi_awready $end
$var reg 32 ' s_axi_wdata[31:0] $end
$var reg 4 ( s_axi_wstrb[3:0] $end
$var reg 1 ) s_axi_wvalid $end
$var reg 1 * s_axi_wready $end
$var reg 2 + s_axi_bresp[1:0] $end
$var reg 1 , s_axi_bvalid $end
$var reg 1 - s_axi_bready $end
$var reg 4 . s_axi_araddr[3:0] $end
$var reg 3 / s_axi_arprot[2:0] $end
$var reg 1 0 s_axi_arvalid $end
$var reg 1 1 s_axi_arready $end
$var reg 32 2 s_axi_rdata[31:0] $end
$var reg 2 3 s_axi_rresp[1:0] $end
$var reg 1 4 s_axi_rvalid $end
$var reg 1 5 s_axi_rready $end
$var reg 1 6 sendit $end
$var reg 1 7 readit $end
$var reg 1 8 freq_div $end
$var reg 16 9 max_count[15:0] $end
$var reg 1 : enable $end
$scope module uut $end
$var reg 1 ; freq_div $end
$var reg 16 < max_count[15:0] $end
$var reg 1 = enable $end
$var reg 1 > s_axi_aclk $end
$var reg 1 ? s_axi_aresetn $end
$var reg 4 @ s_axi_awaddr[3:0] $end
$var reg 3 A s_axi_awprot[2:0] $end
$var reg 1 B s_axi_awvalid $end
$var reg 1 C s_axi_awready $end
$var reg 32 D s_axi_wdata[31:0] $end
$var reg 4 E s_axi_wstrb[3:0] $end
$var reg 1 F s_axi_wvalid $end
$var reg 1 G s_axi_wready $end
$var reg 2 H s_axi_bresp[1:0] $end
$var reg 1 I s_axi_bvalid $end
$var reg 1 J s_axi_bready $end
$var reg 4 K s_axi_araddr[3:0] $end
$var reg 3 L s_axi_arprot[2:0] $end
$var reg 1 M s_axi_arvalid $end
$var reg 1 N s_axi_arready $end
$var reg 32 O s_axi_rdata[31:0] $end
$var reg 2 P s_axi_rresp[1:0] $end
$var reg 1 Q s_axi_rvalid $end
$var reg 1 R s_axi_rready $end
$var reg 4 S axi_awaddr[3:0] $end
$var reg 1 T axi_awready $end
$var reg 1 U axi_wready $end
$var reg 2 V axi_bresp[1:0] $end
$var reg 1 W axi_bvalid $end
$var reg 4 X axi_araddr[3:0] $end
$var reg 1 Y axi_arready $end
$var reg 32 Z axi_rdata[31:0] $end
$var reg 2 [ axi_rresp[1:0] $end
$var reg 1 \ axi_rvalid $end
$var reg 32 ] slv_reg0[31:0] $end
$var reg 32 ^ slv_reg1[31:0] $end
$var reg 32 _ slv_reg2[31:0] $end
$var reg 32 ` slv_reg3[31:0] $end
$var reg 1 a slv_reg_rden $end
$var reg 1 b slv_reg_wren $end
$var reg 32 c reg_data_out[31:0] $end
$var reg 1 d aw_en $end
$upscope $end
$upscope $end
$enddefinitions $end
#0
0!
0"
b0000 #
b000 $
0%
U&
b00000000000000000000000000000000 '
b0000 (
0)
U*
bUU +
U,
0-
b0000 .
b000 /
00
U1
bUUUUUUUUUUUUUUUUUUUUUUUUUUUUUUUU 2
bUU 3
U4
05
06
07
U8
bUUUUUUUUUUUUUUUU 9
U:
U;
bUUUUUUUUUUUUUUUU <
U=
0>
0?
b0000 @
b000 A
0B
UC
b00000000000000000000000000000000 D
b0000 E
0F
UG
bUU H
UI
0J
b0000 K
b000 L
0M
UN
bUUUUUUUUUUUUUUUUUUUUUUUUUUUUUUUU O
bUU P
UQ
0R
bUUUU S
UT
UU
bUU V
UW
bUUUU X
UY
bUUUUUUUUUUUUUUUUUUUUUUUUUUUUUUUU Z
bUU [
U\
bUUUUUUUUUUUUUUUUUUUUUUUUUUUUUUUU ]
bUUUUUUUUUUUUUUUUUUUUUUUUUUUUUUUU ^
bUUUUUUUUUUUUUUUUUUUUUUUUUUUUUUUU _
bUUUUUUUUUUUUUUUUUUUUUUUUUUUUUUUU `
0a
0b
b00000000000000000000000000000000 c
Ud
#2500000
1!
0&
0*
b00 +
0,
01
b00000000000000000000000000000000 2
b00 3
04
08
b0000000000000000 9
0:
0;
b0000000000000000 <
0=
1>
0C
0G
b00 H
0I
0N
b00000000000000000000000000000000 O
b00 P
0Q
b0000 S
0T
0U
b00 V
0W
b1111 X
0Y
b00000000000000000000000000000000 Z
b00 [
0\
b00000000000000000000000000000000 ]
b00000000000000000000000000000000 ^
b00000000000000000000000000000000 _
b00000000000000000000000000000000 `
1d
#5000000
0!
0>
#7500000
1!
1>
#10000000
0!
0>
#12500000
1!
1>
#15000000
0!
1"
b00000000000000000000000000000001 '
b1111 (
16
0>
1?
b00000000000000000000000000000001 D
b1111 E
#16000000
06
#17500000
1!
1>
#20000000
0!
1%
1)
0>
1B
1F
#22500000
1!
1&
1*
1-
1>
1C
1G
1J
1T
1U
1b
0d
#25000000
0!
0>
#27500000
1!
0%
0&
0)
0*
1,
18
1;
1>
0B
0C
0F
0G
1I
0T
0U
1W
b00000000000000000000000000000001 ]
0b
#30000000
0!
0>
#32500000
1!
b0100 #
0,
0-
16
1>
b0100 @
0I
0J
0W
1d
#33500000
06
#35000000
0!
1%
1)
0>
1B
1F
#37500000
1!
1&
1*
1-
1>
1C
1G
1J
b0100 S
1T
1U
1b
0d
#40000000
0!
0>
#42500000
1!
0%
0&
0)
0*
1,
1:
1=
1>
0B
0C
0F
0G
1I
0T
0U
1W
b00000000000000000000000000000001 ^
0b
#45000000
0!
0>
#47500000
1!
b1000 #
b00000000000000000000001100000000 '
0,
0-
16
1>
b1000 @
b00000000000000000000001100000000 D
0I
0J
0W
1d
#48500000
06
#50000000
0!
1%
1)
0>
1B
1F
#52500000
1!
1&
1*
1-
1>
1C
1G
1J
b1000 S
1T
1U
1b
0d
#55000000
0!
0>
#57500000
1!
0%
0&
0)
0*
1,
b0000001100000000 9
b0000001100000000 <
1>
0B
0C
0F
0G
1I
0T
0U
1W
b00000000000000000000001100000000 _
0b
#60000000
0!
0>
#62500000
1!
b0000 #
b00000000000000000000000000000000 '
0,
0-
16
1>
b0000 @
b00000000000000000000000000000000 D
0I
0J
0W
1d
#63500000
06
#65000000
0!
1%
1)
0>
1B
1F
#67500000
1!
1&
1*
1-
1>
1C
1G
1J
b0000 S
1T
1U
1b
0d
#70000000
0!
0>
#72500000
1!
0%
0&
0)
0*
1,
08
0;
1>
0B
0C
0F
0G
1I
0T
0U
1W
b00000000000000000000000000000000 ]
0b
#75000000
0!
0>
#77500000
1!
b0000 (
0,
0-
17
1>
b0000 E
0I
0J
0W
1d
#78500000
07
#80000000
0!
10
15
0>
1M
1R
